pathtemplater/__init__.py
pathtemplater/pathtemplater.py
pathtemplater-1.0.0.dev7.data/data/LICENSE.md
pathtemplater-1.0.0.dev7.dist-info/LICENSE.md
pathtemplater-1.0.0.dev7.dist-info/METADATA
pathtemplater-1.0.0.dev7.dist-info/WHEEL
pathtemplater-1.0.0.dev7.dist-info/top_level.txt
pathtemplater-1.0.0.dev7.dist-info/RECORD
